{
    "key": "group_globeiron_announcement",
    "title": "Announcement Bar",
    "fields": [
        {
            "key": "field_ann_enabled",
            "label": "Enable Announcement Bar",
            "name": "ann_enabled",
            "aria-label": "",
            "type": "true_false",
            "instructions": "Toggle to show or hide the announcement bar sitewide.",
            "required": false,
            "conditional_logic": false,
            "wrapper": {
                "width": "",
                "class": "",
                "id": ""
            },
            "message": "",
            "default_value": 0,
            "ui": 1,
            "ui_on_text": "Enabled",
            "ui_off_text": "Disabled"
        },
        {
            "key": "field_ann_text",
            "label": "Announcement Text",
            "name": "ann_text",
            "aria-label": "",
            "type": "text",
            "instructions": "The message displayed across the top of every page.",
            "required": false,
            "conditional_logic": false,
            "wrapper": {
                "width": "",
                "class": "",
                "id": ""
            },
            "default_value": "",
            "maxlength": "",
            "placeholder": "",
            "prepend": "",
            "append": ""
        },
        {
            "key": "field_ann_url",
            "label": "Link URL (optional)",
            "name": "ann_url",
            "aria-label": "",
            "type": "url",
            "instructions": "",
            "required": false,
            "conditional_logic": false,
            "wrapper": {
                "width": "",
                "class": "",
                "id": ""
            },
            "default_value": "",
            "placeholder": ""
        },
        {
            "key": "field_ann_link_label",
            "label": "Link Label",
            "name": "ann_link_label",
            "aria-label": "",
            "type": "text",
            "instructions": "",
            "required": false,
            "conditional_logic": false,
            "wrapper": {
                "width": "",
                "class": "",
                "id": ""
            },
            "default_value": "Learn more",
            "maxlength": "",
            "placeholder": "",
            "prepend": "",
            "append": ""
        }
    ],
    "location": [
        [
            {
                "param": "options_page",
                "operator": "==",
                "value": "globeiron-announcement"
            }
        ]
    ],
    "menu_order": 0,
    "position": "normal",
    "style": "default",
    "label_placement": "top",
    "instruction_placement": "label",
    "hide_on_screen": [],
    "active": true,
    "description": "",
    "show_in_rest": false
}
